[{"visit_id":"V19114257","rep_id":"11.03","visit_date_plan":"2019-06-12T00:00:00","visit_plan":0,"visit_code":null,"visit_realization":0,"visit_info":"Full Day Meeting","visit_sp":null,"visit_sp_value":null,"dr_code":801008,"visit_plan_verification_status":1,"visit_plan_verification_by":"10.36","visit_plan_verification_date":"2019-06-13T11:37:46.727","visit_real_verification_status":0,"visit_real_verification_by":null,"visit_real_verification_date":null,"visit_date_plan_saved":"2019-06-12T00:00:00","visit_date_plan_updated":null,"visit_date_realization_saved":"2019-06-19T00:00:00","visit_coverage_plan":null,"visit_coverage_real":null,"visit_sign_id":null,"visit_sign_image":"","visit_ordinat":null,"visit_product_count":2,"visit_comment":null},{"visit_id":"V19114258","rep_id":"11.03","visit_date_plan":"2019-06-12T00:00:00","visit_plan":0,"visit_code":null,"visit_realization":0,"visit_info":"Full Day Meeting","visit_sp":null,"visit_sp_value":null,"dr_code":801030,"visit_plan_verification_status":1,"visit_plan_verification_by":"10.36","visit_plan_verification_date":"2019-06-13T11:37:46.727","visit_real_verification_status":0,"visit_real_verification_by":null,"visit_real_verification_date":null,"visit_date_plan_saved":"2019-06-12T00:00:00","visit_date_plan_updated":null,"visit_date_realization_saved":"2019-06-19T00:00:00","visit_coverage_plan":null,"visit_coverage_real":null,"visit_sign_id":null,"visit_sign_image":"","visit_ordinat":null,"visit_product_count":null,"visit_comment":null},{"visit_id":"V19114259","rep_id":"11.03","visit_date_plan":"2019-06-12T00:00:00","visit_plan":0,"visit_code":null,"visit_realization":0,"visit_info":"Full Day Meeting","visit_sp":null,"visit_sp_value":null,"dr_code":821021,"visit_plan_verification_status":1,"visit_plan_verification_by":"10.36","visit_plan_verification_date":"2019-06-13T11:37:46.727","visit_real_verification_status":0,"visit_real_verification_by":null,"visit_real_verification_date":null,"visit_date_plan_saved":"2019-06-12T00:00:00","visit_date_plan_updated":null,"visit_date_realization_saved":"2019-06-19T00:00:00","visit_coverage_plan":null,"visit_coverage_real":null,"visit_sign_id":null,"visit_sign_image":"","visit_ordinat":null,"visit_product_count":null,"visit_comment":null},{"visit_id":"V19114260","rep_id":"11.03","visit_date_plan":"2019-06-12T00:00:00","visit_plan":0,"visit_code":null,"visit_realization":0,"visit_info":"Full Day Meeting","visit_sp":null,"visit_sp_value":null,"dr_code":821009,"visit_plan_verification_status":1,"visit_plan_verification_by":"10.36","visit_plan_verification_date":"2019-06-13T11:37:46.727","visit_real_verification_status":0,"visit_real_verification_by":null,"visit_real_verification_date":null,"visit_date_plan_saved":"2019-06-12T00:00:00","visit_date_plan_updated":null,"visit_date_realization_saved":"2019-06-19T00:00:00","visit_coverage_plan":null,"visit_coverage_real":null,"visit_sign_id":null,"visit_sign_image":"","visit_ordinat":null,"visit_product_count":1,"visit_comment":null},{"visit_id":"V19114261","rep_id":"11.03","visit_date_plan":"2019-06-12T00:00:00","visit_plan":0,"visit_code":null,"visit_realization":0,"visit_info":"Full Day Meeting","visit_sp":null,"visit_sp_value":null,"dr_code":2141007,"visit_plan_verification_status":1,"visit_plan_verification_by":"10.36","visit_plan_verification_date":"2019-06-13T11:37:46.727","visit_real_verification_status":0,"visit_real_verification_by":null,"visit_real_verification_date":null,"visit_date_plan_saved":"2019-06-12T00:00:00","visit_date_plan_updated":null,"visit_date_realization_saved":"2019-06-19T00:00:00","visit_coverage_plan":null,"visit_coverage_real":null,"visit_sign_id":null,"visit_sign_image":"","visit_ordinat":null,"visit_product_count":null,"visit_comment":null},{"visit_id":"V19114262","rep_id":"11.03","visit_date_plan":"2019-06-12T00:00:00","visit_plan":0,"visit_code":null,"visit_realization":0,"visit_info":"Full Day Meeting","visit_sp":null,"visit_sp_value":null,"dr_code":3142007,"visit_plan_verification_status":1,"visit_plan_verification_by":"10.36","visit_plan_verification_date":"2019-06-13T11:37:46.727","visit_real_verification_status":0,"visit_real_verification_by":null,"visit_real_verification_date":null,"visit_date_plan_saved":"2019-06-12T00:00:00","visit_date_plan_updated":null,"visit_date_realization_saved":"2019-06-19T00:00:00","visit_coverage_plan":null,"visit_coverage_real":null,"visit_sign_id":null,"visit_sign_image":"","visit_ordinat":null,"visit_product_count":null,"visit_comment":null},{"visit_id":"V19114281","rep_id":"11.03","visit_date_plan":"2019-06-14T00:00:00","visit_plan":0,"visit_code":null,"visit_realization":0,"visit_info":"Full Leave","visit_sp":null,"visit_sp_value":null,"dr_code":801002,"visit_plan_verification_status":1,"visit_plan_verification_by":"10.36","visit_plan_verification_date":"2019-06-13T11:37:46.727","visit_real_verification_status":0,"visit_real_verification_by":null,"visit_real_verification_date":null,"visit_date_plan_saved":"2019-06-12T00:00:00","visit_date_plan_updated":null,"visit_date_realization_saved":"2019-06-18T00:00:00","visit_coverage_plan":null,"visit_coverage_real":null,"visit_sign_id":null,"visit_sign_image":"","visit_ordinat":null,"visit_product_count":1,"visit_comment":null},{"visit_id":"V19114282","rep_id":"11.03","visit_date_plan":"2019-06-14T00:00:00","visit_plan":0,"visit_code":null,"visit_realization":0,"visit_info":"Full Leave","visit_sp":null,"visit_sp_value":null,"dr_code":2141006,"visit_plan_verification_status":1,"visit_plan_verification_by":"10.36","visit_plan_verification_date":"2019-06-13T11:37:46.727","visit_real_verification_status":0,"visit_real_verification_by":null,"visit_real_verification_date":null,"visit_date_plan_saved":"2019-06-12T00:00:00","visit_date_plan_updated":null,"visit_date_realization_saved":"2019-06-18T00:00:00","visit_coverage_plan":null,"visit_coverage_real":null,"visit_sign_id":null,"visit_sign_image":"","visit_ordinat":null,"visit_product_count":1,"visit_comment":null},{"visit_id":"V19114283","rep_id":"11.03","visit_date_plan":"2019-06-14T00:00:00","visit_plan":0,"visit_code":null,"visit_realization":0,"visit_info":"Full Leave","visit_sp":null,"visit_sp_value":null,"dr_code":3142009,"visit_plan_verification_status":1,"visit_plan_verification_by":"10.36","visit_plan_verification_date":"2019-06-13T11:37:46.727","visit_real_verification_status":0,"visit_real_verification_by":null,"visit_real_verification_date":null,"visit_date_plan_saved":"2019-06-12T00:00:00","visit_date_plan_updated":null,"visit_date_realization_saved":"2019-06-18T00:00:00","visit_coverage_plan":null,"visit_coverage_real":null,"visit_sign_id":null,"visit_sign_image":"","visit_ordinat":null,"visit_product_count":1,"visit_comment":null},{"visit_id":"V19114284","rep_id":"11.03","visit_date_plan":"2019-06-14T00:00:00","visit_plan":0,"visit_code":null,"visit_realization":0,"visit_info":"Full Leave","visit_sp":null,"visit_sp_value":null,"dr_code":282005,"visit_plan_verification_status":1,"visit_plan_verification_by":"10.36","visit_plan_verification_date":"2019-06-13T11:37:46.727","visit_real_verification_status":0,"visit_real_verification_by":null,"visit_real_verification_date":null,"visit_date_plan_saved":"2019-06-12T00:00:00","visit_date_plan_updated":null,"visit_date_realization_saved":"2019-06-18T00:00:00","visit_coverage_plan":null,"visit_coverage_real":null,"visit_sign_id":null,"visit_sign_image":"","visit_ordinat":null,"visit_product_count":1,"visit_comment":null},{"visit_id":"V19114285","rep_id":"11.03","visit_date_plan":"2019-06-14T00:00:00","visit_plan":0,"visit_code":null,"visit_realization":0,"visit_info":"Full Leave","visit_sp":null,"visit_sp_value":null,"dr_code":353143,"visit_plan_verification_status":1,"visit_plan_verification_by":"10.36","visit_plan_verification_date":"2019-06-13T11:37:46.727","visit_real_verification_status":0,"visit_real_verification_by":null,"visit_real_verification_date":null,"visit_date_plan_saved":"2019-06-12T00:00:00","visit_date_plan_updated":null,"visit_date_realization_saved":"2019-06-18T00:00:00","visit_coverage_plan":null,"visit_coverage_real":null,"visit_sign_id":null,"visit_sign_image":"","visit_ordinat":null,"visit_product_count":1,"visit_comment":null},{"visit_id":"V19114286","rep_id":"11.03","visit_date_plan":"2019-06-14T00:00:00","visit_plan":0,"visit_code":null,"visit_realization":0,"visit_info":"Full Leave","visit_sp":null,"visit_sp_value":null,"dr_code":821001,"visit_plan_verification_status":1,"visit_plan_verification_by":"10.36","visit_plan_verification_date":"2019-06-13T11:37:46.727","visit_real_verification_status":0,"visit_real_verification_by":null,"visit_real_verification_date":null,"visit_date_plan_saved":"2019-06-12T00:00:00","visit_date_plan_updated":null,"visit_date_realization_saved":"2019-06-18T00:00:00","visit_coverage_plan":null,"visit_coverage_real":null,"visit_sign_id":null,"visit_sign_image":"","visit_ordinat":null,"visit_product_count":2,"visit_comment":null},{"visit_id":"V19114288","rep_id":"11.03","visit_date_plan":"2019-06-17T00:00:00","visit_plan":1,"visit_code":null,"visit_realization":1,"visit_info":"","visit_sp":null,"visit_sp_value":null,"dr_code":282026,"visit_plan_verification_status":1,"visit_plan_verification_by":"10.36","visit_plan_verification_date":"2019-06-13T11:37:46.727","visit_real_verification_status":0,"visit_real_verification_by":null,"visit_real_verification_date":null,"visit_date_plan_saved":"2019-06-12T00:00:00","visit_date_plan_updated":null,"visit_date_realization_saved":"2019-06-17T19:02:58.4","visit_coverage_plan":null,"visit_coverage_real":null,"visit_sign_id":null,"visit_sign_image":"","visit_ordinat":null,"visit_product_count":1,"visit_comment":null},{"visit_id":"V19114289","rep_id":"11.03","visit_date_plan":"2019-06-18T00:00:00","visit_plan":1,"visit_code":null,"visit_realization":0,"visit_info":null,"visit_sp":null,"visit_sp_value":null,"dr_code":551003,"visit_plan_verification_status":1,"visit_plan_verification_by":"10.36","visit_plan_verification_date":"2019-06-13T11:37:46.727","visit_real_verification_status":0,"visit_real_verification_by":null,"visit_real_verification_date":null,"visit_date_plan_saved":"2019-06-12T00:00:00","visit_date_plan_updated":null,"visit_date_realization_saved":null,"visit_coverage_plan":null,"visit_coverage_real":null,"visit_sign_id":null,"visit_sign_image":"","visit_ordinat":null,"visit_product_count":1,"visit_comment":null},{"visit_id":"V19114290","rep_id":"11.03","visit_date_plan":"2019-06-17T00:00:00","visit_plan":1,"visit_code":null,"visit_realization":1,"visit_info":"","visit_sp":null,"visit_sp_value":null,"dr_code":821001,"visit_plan_verification_status":1,"visit_plan_verification_by":"10.36","visit_plan_verification_date":"2019-06-13T11:37:46.727","visit_real_verification_status":0,"visit_real_verification_by":null,"visit_real_verification_date":null,"visit_date_plan_saved":"2019-06-12T00:00:00","visit_date_plan_updated":null,"visit_date_realization_saved":"2019-06-17T17:41:24.7","visit_coverage_plan":null,"visit_coverage_real":null,"visit_sign_id":null,"visit_sign_image":"","visit_ordinat":null,"visit_product_count":2,"visit_comment":null},{"visit_id":"V19114291","rep_id":"11.03","visit_date_plan":"2019-06-17T00:00:00","visit_plan":1,"visit_code":null,"visit_realization":1,"visit_info":"","visit_sp":null,"visit_sp_value":null,"dr_code":821022,"visit_plan_verification_status":1,"visit_plan_verification_by":"10.36","visit_plan_verification_date":"2019-06-13T11:37:46.727","visit_real_verification_status":0,"visit_real_verification_by":null,"visit_real_verification_date":null,"visit_date_plan_saved":"2019-06-12T00:00:00","visit_date_plan_updated":null,"visit_date_realization_saved":"2019-06-18T12:50:44.057","visit_coverage_plan":null,"visit_coverage_real":null,"visit_sign_id":null,"visit_sign_image":"","visit_ordinat":null,"visit_product_count":2,"visit_comment":null},{"visit_id":"V19114292","rep_id":"11.03","visit_date_plan":"2019-06-17T00:00:00","visit_plan":1,"visit_code":null,"visit_realization":1,"visit_info":"","visit_sp":"0","visit_sp_value":null,"dr_code":801008,"visit_plan_verification_status":1,"visit_plan_verification_by":"10.36","visit_plan_verification_date":"2019-06-13T11:37:46.727","visit_real_verification_status":0,"visit_real_verification_by":null,"visit_real_verification_date":null,"visit_date_plan_saved":"2019-06-12T00:00:00","visit_date_plan_updated":null,"visit_date_realization_saved":"2019-06-18T11:37:49.47","visit_coverage_plan":null,"visit_coverage_real":null,"visit_sign_id":null,"visit_sign_image":"","visit_ordinat":null,"visit_product_count":2,"visit_comment":null},{"visit_id":"V19114293","rep_id":"11.03","visit_date_plan":"2019-06-17T00:00:00","visit_plan":1,"visit_code":null,"visit_realization":0,"visit_info":null,"visit_sp":null,"visit_sp_value":null,"dr_code":272001,"visit_plan_verification_status":1,"visit_plan_verification_by":"10.36","visit_plan_verification_date":"2019-06-13T11:37:46.727","visit_real_verification_status":0,"visit_real_verification_by":null,"visit_real_verification_date":null,"visit_date_plan_saved":"2019-06-12T00:00:00","visit_date_plan_updated":null,"visit_date_realization_saved":null,"visit_coverage_plan":null,"visit_coverage_real":null,"visit_sign_id":null,"visit_sign_image":"","visit_ordinat":null,"visit_product_count":1,"visit_comment":null},{"visit_id":"V19114307","rep_id":"11.03","visit_date_plan":"2019-06-18T00:00:00","visit_plan":1,"visit_code":null,"visit_realization":0,"visit_info":null,"visit_sp":null,"visit_sp_value":null,"dr_code":801002,"visit_plan_verification_status":1,"visit_plan_verification_by":"10.36","visit_plan_verification_date":"2019-06-13T11:37:46.727","visit_real_verification_status":0,"visit_real_verification_by":null,"visit_real_verification_date":null,"visit_date_plan_saved":"2019-06-12T00:00:00","visit_date_plan_updated":null,"visit_date_realization_saved":null,"visit_coverage_plan":null,"visit_coverage_real":null,"visit_sign_id":null,"visit_sign_image":"","visit_ordinat":null,"visit_product_count":1,"visit_comment":null},{"visit_id":"V19114308","rep_id":"11.03","visit_date_plan":"2019-06-18T00:00:00","visit_plan":1,"visit_code":null,"visit_realization":0,"visit_info":null,"visit_sp":null,"visit_sp_value":null,"dr_code":801011,"visit_plan_verification_status":1,"visit_plan_verification_by":"10.36","visit_plan_verification_date":"2019-06-13T11:37:46.727","visit_real_verification_status":0,"visit_real_verification_by":null,"visit_real_verification_date":null,"visit_date_plan_saved":"2019-06-12T00:00:00","visit_date_plan_updated":null,"visit_date_realization_saved":null,"visit_coverage_plan":null,"visit_coverage_real":null,"visit_sign_id":null,"visit_sign_image":"","visit_ordinat":null,"visit_product_count":1,"visit_comment":null},{"visit_id":"V19114309","rep_id":"11.03","visit_date_plan":"2019-06-18T00:00:00","visit_plan":1,"visit_code":null,"visit_realization":0,"visit_info":null,"visit_sp":null,"visit_sp_value":null,"dr_code":801013,"visit_plan_verification_status":1,"visit_plan_verification_by":"10.36","visit_plan_verification_date":"2019-06-13T11:37:46.727","visit_real_verification_status":0,"visit_real_verification_by":null,"visit_real_verification_date":null,"visit_date_plan_saved":"2019-06-12T00:00:00","visit_date_plan_updated":null,"visit_date_realization_saved":null,"visit_coverage_plan":null,"visit_coverage_real":null,"visit_sign_id":null,"visit_sign_image":"","visit_ordinat":null,"visit_product_count":2,"visit_comment":null},{"visit_id":"V19114310","rep_id":"11.03","visit_date_plan":"2019-06-18T00:00:00","visit_plan":1,"visit_code":null,"visit_realization":0,"visit_info":null,"visit_sp":null,"visit_sp_value":null,"dr_code":801027,"visit_plan_verification_status":1,"visit_plan_verification_by":"10.36","visit_plan_verification_date":"2019-06-13T11:37:46.727","visit_real_verification_status":0,"visit_real_verification_by":null,"visit_real_verification_date":null,"visit_date_plan_saved":"2019-06-12T00:00:00","visit_date_plan_updated":null,"visit_date_realization_saved":null,"visit_coverage_plan":null,"visit_coverage_real":null,"visit_sign_id":null,"visit_sign_image":"","visit_ordinat":null,"visit_product_count":1,"visit_comment":null},{"visit_id":"V19114311","rep_id":"11.03","visit_date_plan":"2019-06-18T00:00:00","visit_plan":1,"visit_code":null,"visit_realization":1,"visit_info":"","visit_sp":"0","visit_sp_value":null,"dr_code":821009,"visit_plan_verification_status":1,"visit_plan_verification_by":"10.36","visit_plan_verification_date":"2019-06-13T11:37:46.727","visit_real_verification_status":0,"visit_real_verification_by":null,"visit_real_verification_date":null,"visit_date_plan_saved":"2019-06-12T00:00:00","visit_date_plan_updated":null,"visit_date_realization_saved":"2019-06-18T12:57:20.03","visit_coverage_plan":null,"visit_coverage_real":null,"visit_sign_id":null,"visit_sign_image":"","visit_ordinat":null,"visit_product_count":1,"visit_comment":null},{"visit_id":"V19114312","rep_id":"11.03","visit_date_plan":"2019-06-18T00:00:00","visit_plan":1,"visit_code":null,"visit_realization":0,"visit_info":null,"visit_sp":null,"visit_sp_value":null,"dr_code":425003,"visit_plan_verification_status":1,"visit_plan_verification_by":"10.36","visit_plan_verification_date":"2019-06-13T11:37:46.727","visit_real_verification_status":0,"visit_real_verification_by":null,"visit_real_verification_date":null,"visit_date_plan_saved":"2019-06-12T00:00:00","visit_date_plan_updated":null,"visit_date_realization_saved":null,"visit_coverage_plan":null,"visit_coverage_real":null,"visit_sign_id":null,"visit_sign_image":"","visit_ordinat":null,"visit_product_count":1,"visit_comment":null},{"visit_id":"V19114314","rep_id":"11.03","visit_date_plan":"2019-06-19T00:00:00","visit_plan":1,"visit_code":null,"visit_realization":0,"visit_info":null,"visit_sp":null,"visit_sp_value":null,"dr_code":801005,"visit_plan_verification_status":1,"visit_plan_verification_by":"10.36","visit_plan_verification_date":"2019-06-13T11:37:46.727","visit_real_verification_status":0,"visit_real_verification_by":null,"visit_real_verification_date":null,"visit_date_plan_saved":"2019-06-12T00:00:00","visit_date_plan_updated":null,"visit_date_realization_saved":null,"visit_coverage_plan":null,"visit_coverage_real":null,"visit_sign_id":null,"visit_sign_image":"","visit_ordinat":null,"visit_product_count":1,"visit_comment":null},{"visit_id":"V19114315","rep_id":"11.03","visit_date_plan":"2019-06-19T00:00:00","visit_plan":1,"visit_code":null,"visit_realization":0,"visit_info":null,"visit_sp":null,"visit_sp_value":null,"dr_code":801030,"visit_plan_verification_status":1,"visit_plan_verification_by":"10.36","visit_plan_verification_date":"2019-06-13T11:37:46.727","visit_real_verification_status":0,"visit_real_verification_by":null,"visit_real_verification_date":null,"visit_date_plan_saved":"2019-06-12T00:00:00","visit_date_plan_updated":null,"visit_date_realization_saved":null,"visit_coverage_plan":null,"visit_coverage_real":null,"visit_sign_id":null,"visit_sign_image":"","visit_ordinat":null,"visit_product_count":null,"visit_comment":null},{"visit_id":"V19114316","rep_id":"11.03","visit_date_plan":"2019-06-19T00:00:00","visit_plan":1,"visit_code":null,"visit_realization":1,"visit_info":"","visit_sp":null,"visit_sp_value":null,"dr_code":821005,"visit_plan_verification_status":1,"visit_plan_verification_by":"10.36","visit_plan_verification_date":"2019-06-13T11:37:46.727","visit_real_verification_status":0,"visit_real_verification_by":null,"visit_real_verification_date":null,"visit_date_plan_saved":"2019-06-12T00:00:00","visit_date_plan_updated":null,"visit_date_realization_saved":"2019-06-19T13:04:16.3","visit_coverage_plan":null,"visit_coverage_real":null,"visit_sign_id":null,"visit_sign_image":"","visit_ordinat":null,"visit_product_count":1,"visit_comment":null},{"visit_id":"V19114317","rep_id":"11.03","visit_date_plan":"2019-06-19T00:00:00","visit_plan":1,"visit_code":null,"visit_realization":0,"visit_info":null,"visit_sp":null,"visit_sp_value":null,"dr_code":821021,"visit_plan_verification_status":1,"visit_plan_verification_by":"10.36","visit_plan_verification_date":"2019-06-13T11:37:46.727","visit_real_verification_status":0,"visit_real_verification_by":null,"visit_real_verification_date":null,"visit_date_plan_saved":"2019-06-12T00:00:00","visit_date_plan_updated":null,"visit_date_realization_saved":null,"visit_coverage_plan":null,"visit_coverage_real":null,"visit_sign_id":null,"visit_sign_image":"","visit_ordinat":null,"visit_product_count":null,"visit_comment":null},{"visit_id":"V19114318","rep_id":"11.03","visit_date_plan":"2019-06-19T00:00:00","visit_plan":1,"visit_code":null,"visit_realization":0,"visit_info":null,"visit_sp":null,"visit_sp_value":null,"dr_code":2141007,"visit_plan_verification_status":1,"visit_plan_verification_by":"10.36","visit_plan_verification_date":"2019-06-13T11:37:46.727","visit_real_verification_status":0,"visit_real_verification_by":null,"visit_real_verification_date":null,"visit_date_plan_saved":"2019-06-12T00:00:00","visit_date_plan_updated":null,"visit_date_realization_saved":null,"visit_coverage_plan":null,"visit_coverage_real":null,"visit_sign_id":null,"visit_sign_image":"","visit_ordinat":null,"visit_product_count":null,"visit_comment":null},{"visit_id":"V19114319","rep_id":"11.03","visit_date_plan":"2019-06-19T00:00:00","visit_plan":1,"visit_code":null,"visit_realization":0,"visit_info":null,"visit_sp":null,"visit_sp_value":null,"dr_code":282005,"visit_plan_verification_status":1,"visit_plan_verification_by":"10.36","visit_plan_verification_date":"2019-06-13T11:37:46.727","visit_real_verification_status":0,"visit_real_verification_by":null,"visit_real_verification_date":null,"visit_date_plan_saved":"2019-06-12T00:00:00","visit_date_plan_updated":null,"visit_date_realization_saved":null,"visit_coverage_plan":null,"visit_coverage_real":null,"visit_sign_id":null,"visit_sign_image":"","visit_ordinat":null,"visit_product_count":1,"visit_comment":null},{"visit_id":"V19114320","rep_id":"11.03","visit_date_plan":"2019-06-20T00:00:00","visit_plan":1,"visit_code":null,"visit_realization":0,"visit_info":null,"visit_sp":null,"visit_sp_value":null,"dr_code":801017,"visit_plan_verification_status":1,"visit_plan_verification_by":"10.36","visit_plan_verification_date":"2019-06-13T11:37:46.727","visit_real_verification_status":0,"visit_real_verification_by":null,"visit_real_verification_date":null,"visit_date_plan_saved":"2019-06-12T00:00:00","visit_date_plan_updated":null,"visit_date_realization_saved":null,"visit_coverage_plan":null,"visit_coverage_real":null,"visit_sign_id":null,"visit_sign_image":"","visit_ordinat":null,"visit_product_count":1,"visit_comment":null},{"visit_id":"V19114321","rep_id":"11.03","visit_date_plan":"2019-06-20T00:00:00","visit_plan":1,"visit_code":null,"visit_realization":0,"visit_info":null,"visit_sp":null,"visit_sp_value":null,"dr_code":801024,"visit_plan_verification_status":1,"visit_plan_verification_by":"10.36","visit_plan_verification_date":"2019-06-13T11:37:46.727","visit_real_verification_status":0,"visit_real_verification_by":null,"visit_real_verification_date":null,"visit_date_plan_saved":"2019-06-12T00:00:00","visit_date_plan_updated":null,"visit_date_realization_saved":null,"visit_coverage_plan":null,"visit_coverage_real":null,"visit_sign_id":null,"visit_sign_image":"","visit_ordinat":null,"visit_product_count":1,"visit_comment":null},{"visit_id":"V19114322","rep_id":"11.03","visit_date_plan":"2019-06-20T00:00:00","visit_plan":1,"visit_code":null,"visit_realization":0,"visit_info":null,"visit_sp":null,"visit_sp_value":null,"dr_code":821004,"visit_plan_verification_status":1,"visit_plan_verification_by":"10.36","visit_plan_verification_date":"2019-06-13T11:37:46.727","visit_real_verification_status":0,"visit_real_verification_by":null,"visit_real_verification_date":null,"visit_date_plan_saved":"2019-06-12T00:00:00","visit_date_plan_updated":null,"visit_date_realization_saved":null,"visit_coverage_plan":null,"visit_coverage_real":null,"visit_sign_id":null,"visit_sign_image":"","visit_ordinat":null,"visit_product_count":1,"visit_comment":null},{"visit_id":"V19114323","rep_id":"11.03","visit_date_plan":"2019-06-20T00:00:00","visit_plan":1,"visit_code":null,"visit_realization":0,"visit_info":null,"visit_sp":null,"visit_sp_value":null,"dr_code":821018,"visit_plan_verification_status":1,"visit_plan_verification_by":"10.36","visit_plan_verification_date":"2019-06-13T11:37:46.727","visit_real_verification_status":0,"visit_real_verification_by":null,"visit_real_verification_date":null,"visit_date_plan_saved":"2019-06-12T00:00:00","visit_date_plan_updated":null,"visit_date_realization_saved":null,"visit_coverage_plan":null,"visit_coverage_real":null,"visit_sign_id":null,"visit_sign_image":"","visit_ordinat":null,"visit_product_count":2,"visit_comment":null},{"visit_id":"V19114324","rep_id":"11.03","visit_date_plan":"2019-06-20T00:00:00","visit_plan":1,"visit_code":null,"visit_realization":0,"visit_info":null,"visit_sp":null,"visit_sp_value":null,"dr_code":2141006,"visit_plan_verification_status":1,"visit_plan_verification_by":"10.36","visit_plan_verification_date":"2019-06-13T11:37:46.727","visit_real_verification_status":0,"visit_real_verification_by":null,"visit_real_verification_date":null,"visit_date_plan_saved":"2019-06-12T00:00:00","visit_date_plan_updated":null,"visit_date_realization_saved":null,"visit_coverage_plan":null,"visit_coverage_real":null,"visit_sign_id":null,"visit_sign_image":"","visit_ordinat":null,"visit_product_count":1,"visit_comment":null},{"visit_id":"V19114325","rep_id":"11.03","visit_date_plan":"2019-06-20T00:00:00","visit_plan":1,"visit_code":null,"visit_realization":0,"visit_info":null,"visit_sp":null,"visit_sp_value":null,"dr_code":3142010,"visit_plan_verification_status":1,"visit_plan_verification_by":"10.36","visit_plan_verification_date":"2019-06-13T11:37:46.727","visit_real_verification_status":0,"visit_real_verification_by":null,"visit_real_verification_date":null,"visit_date_plan_saved":"2019-06-12T00:00:00","visit_date_plan_updated":null,"visit_date_realization_saved":null,"visit_coverage_plan":null,"visit_coverage_real":null,"visit_sign_id":null,"visit_sign_image":"","visit_ordinat":null,"visit_product_count":1,"visit_comment":null},{"visit_id":"V19114326","rep_id":"11.03","visit_date_plan":"2019-06-21T00:00:00","visit_plan":1,"visit_code":null,"visit_realization":0,"visit_info":null,"visit_sp":null,"visit_sp_value":null,"dr_code":821002,"visit_plan_verification_status":1,"visit_plan_verification_by":"10.36","visit_plan_verification_date":"2019-06-13T11:37:46.727","visit_real_verification_status":0,"visit_real_verification_by":null,"visit_real_verification_date":null,"visit_date_plan_saved":"2019-06-12T00:00:00","visit_date_plan_updated":null,"visit_date_realization_saved":null,"visit_coverage_plan":null,"visit_coverage_real":null,"visit_sign_id":null,"visit_sign_image":"","visit_ordinat":null,"visit_product_count":1,"visit_comment":null},{"visit_id":"V19114327","rep_id":"11.03","visit_date_plan":"2019-06-21T00:00:00","visit_plan":1,"visit_code":null,"visit_realization":0,"visit_info":null,"visit_sp":null,"visit_sp_value":null,"dr_code":2141005,"visit_plan_verification_status":1,"visit_plan_verification_by":"10.36","visit_plan_verification_date":"2019-06-13T11:37:46.727","visit_real_verification_status":0,"visit_real_verification_by":null,"visit_real_verification_date":null,"visit_date_plan_saved":"2019-06-12T00:00:00","visit_date_plan_updated":null,"visit_date_realization_saved":null,"visit_coverage_plan":null,"visit_coverage_real":null,"visit_sign_id":null,"visit_sign_image":"","visit_ordinat":null,"visit_product_count":1,"visit_comment":null},{"visit_id":"V19114328","rep_id":"11.03","visit_date_plan":"2019-06-21T00:00:00","visit_plan":1,"visit_code":null,"visit_realization":0,"visit_info":null,"visit_sp":null,"visit_sp_value":null,"dr_code":2141008,"visit_plan_verification_status":1,"visit_plan_verification_by":"10.36","visit_plan_verification_date":"2019-06-13T11:37:46.727","visit_real_verification_status":0,"visit_real_verification_by":null,"visit_real_verification_date":null,"visit_date_plan_saved":"2019-06-12T00:00:00","visit_date_plan_updated":null,"visit_date_realization_saved":null,"visit_coverage_plan":null,"visit_coverage_real":null,"visit_sign_id":null,"visit_sign_image":"","visit_ordinat":null,"visit_product_count":1,"visit_comment":null},{"visit_id":"V19114329","rep_id":"11.03","visit_date_plan":"2019-06-21T00:00:00","visit_plan":1,"visit_code":null,"visit_realization":0,"visit_info":null,"visit_sp":null,"visit_sp_value":null,"dr_code":3142009,"visit_plan_verification_status":1,"visit_plan_verification_by":"10.36","visit_plan_verification_date":"2019-06-13T11:37:46.727","visit_real_verification_status":0,"visit_real_verification_by":null,"visit_real_verification_date":null,"visit_date_plan_saved":"2019-06-12T00:00:00","visit_date_plan_updated":null,"visit_date_realization_saved":null,"visit_coverage_plan":null,"visit_coverage_real":null,"visit_sign_id":null,"visit_sign_image":"","visit_ordinat":null,"visit_product_count":1,"visit_comment":null},{"visit_id":"V19114330","rep_id":"11.03","visit_date_plan":"2019-06-21T00:00:00","visit_plan":1,"visit_code":null,"visit_realization":0,"visit_info":null,"visit_sp":null,"visit_sp_value":null,"dr_code":455018,"visit_plan_verification_status":1,"visit_plan_verification_by":"10.36","visit_plan_verification_date":"2019-06-13T11:37:46.727","visit_real_verification_status":0,"visit_real_verification_by":null,"visit_real_verification_date":null,"visit_date_plan_saved":"2019-06-12T00:00:00","visit_date_plan_updated":null,"visit_date_realization_saved":null,"visit_coverage_plan":null,"visit_coverage_real":null,"visit_sign_id":null,"visit_sign_image":"","visit_ordinat":null,"visit_product_count":1,"visit_comment":null},{"visit_id":"V19114331","rep_id":"11.03","visit_date_plan":"2019-06-21T00:00:00","visit_plan":1,"visit_code":null,"visit_realization":0,"visit_info":null,"visit_sp":null,"visit_sp_value":null,"dr_code":353110,"visit_plan_verification_status":1,"visit_plan_verification_by":"10.36","visit_plan_verification_date":"2019-06-13T11:37:46.727","visit_real_verification_status":0,"visit_real_verification_by":null,"visit_real_verification_date":null,"visit_date_plan_saved":"2019-06-12T00:00:00","visit_date_plan_updated":null,"visit_date_realization_saved":null,"visit_coverage_plan":null,"visit_coverage_real":null,"visit_sign_id":null,"visit_sign_image":"","visit_ordinat":null,"visit_product_count":1,"visit_comment":null},{"visit_id":"V19114332","rep_id":"11.03","visit_date_plan":"2019-06-24T00:00:00","visit_plan":1,"visit_code":null,"visit_realization":0,"visit_info":null,"visit_sp":null,"visit_sp_value":null,"dr_code":282026,"visit_plan_verification_status":1,"visit_plan_verification_by":"10.36","visit_plan_verification_date":"2019-06-13T11:37:46.727","visit_real_verification_status":0,"visit_real_verification_by":null,"visit_real_verification_date":null,"visit_date_plan_saved":"2019-06-12T00:00:00","visit_date_plan_updated":null,"visit_date_realization_saved":null,"visit_coverage_plan":null,"visit_coverage_real":null,"visit_sign_id":null,"visit_sign_image":"","visit_ordinat":null,"visit_product_count":1,"visit_comment":null},{"visit_id":"V19114333","rep_id":"11.03","visit_date_plan":"2019-06-24T00:00:00","visit_plan":1,"visit_code":null,"visit_realization":0,"visit_info":null,"visit_sp":null,"visit_sp_value":null,"dr_code":801008,"visit_plan_verification_status":1,"visit_plan_verification_by":"10.36","visit_plan_verification_date":"2019-06-13T11:37:46.727","visit_real_verification_status":0,"visit_real_verification_by":null,"visit_real_verification_date":null,"visit_date_plan_saved":"2019-06-12T00:00:00","visit_date_plan_updated":null,"visit_date_realization_saved":null,"visit_coverage_plan":null,"visit_coverage_real":null,"visit_sign_id":null,"visit_sign_image":"","visit_ordinat":null,"visit_product_count":2,"visit_comment":null},{"visit_id":"V19114334","rep_id":"11.03","visit_date_plan":"2019-06-24T00:00:00","visit_plan":1,"visit_code":null,"visit_realization":0,"visit_info":null,"visit_sp":null,"visit_sp_value":null,"dr_code":821001,"visit_plan_verification_status":1,"visit_plan_verification_by":"10.36","visit_plan_verification_date":"2019-06-13T11:37:46.727","visit_real_verification_status":0,"visit_real_verification_by":null,"visit_real_verification_date":null,"visit_date_plan_saved":"2019-06-12T00:00:00","visit_date_plan_updated":null,"visit_date_realization_saved":null,"visit_coverage_plan":null,"visit_coverage_real":null,"visit_sign_id":null,"visit_sign_image":"","visit_ordinat":null,"visit_product_count":2,"visit_comment":null},{"visit_id":"V19114335","rep_id":"11.03","visit_date_plan":"2019-06-24T00:00:00","visit_plan":1,"visit_code":null,"visit_realization":0,"visit_info":null,"visit_sp":null,"visit_sp_value":null,"dr_code":821022,"visit_plan_verification_status":1,"visit_plan_verification_by":"10.36","visit_plan_verification_date":"2019-06-13T11:37:46.727","visit_real_verification_status":0,"visit_real_verification_by":null,"visit_real_verification_date":null,"visit_date_plan_saved":"2019-06-12T00:00:00","visit_date_plan_updated":null,"visit_date_realization_saved":null,"visit_coverage_plan":null,"visit_coverage_real":null,"visit_sign_id":null,"visit_sign_image":"","visit_ordinat":null,"visit_product_count":2,"visit_comment":null},{"visit_id":"V19114336","rep_id":"11.03","visit_date_plan":"2019-06-24T00:00:00","visit_plan":1,"visit_code":null,"visit_realization":0,"visit_info":null,"visit_sp":null,"visit_sp_value":null,"dr_code":3142008,"visit_plan_verification_status":1,"visit_plan_verification_by":"10.36","visit_plan_verification_date":"2019-06-13T11:37:46.727","visit_real_verification_status":0,"visit_real_verification_by":null,"visit_real_verification_date":null,"visit_date_plan_saved":"2019-06-12T00:00:00","visit_date_plan_updated":null,"visit_date_realization_saved":null,"visit_coverage_plan":null,"visit_coverage_real":null,"visit_sign_id":null,"visit_sign_image":"","visit_ordinat":null,"visit_product_count":1,"visit_comment":null},{"visit_id":"V19114337","rep_id":"11.03","visit_date_plan":"2019-06-24T00:00:00","visit_plan":1,"visit_code":null,"visit_realization":0,"visit_info":null,"visit_sp":null,"visit_sp_value":null,"dr_code":551003,"visit_plan_verification_status":1,"visit_plan_verification_by":"10.36","visit_plan_verification_date":"2019-06-13T11:37:46.727","visit_real_verification_status":0,"visit_real_verification_by":null,"visit_real_verification_date":null,"visit_date_plan_saved":"2019-06-12T00:00:00","visit_date_plan_updated":null,"visit_date_realization_saved":null,"visit_coverage_plan":null,"visit_coverage_real":null,"visit_sign_id":null,"visit_sign_image":"","visit_ordinat":null,"visit_product_count":1,"visit_comment":null},{"visit_id":"V19114338","rep_id":"11.03","visit_date_plan":"2019-06-25T00:00:00","visit_plan":1,"visit_code":null,"visit_realization":0,"visit_info":null,"visit_sp":null,"visit_sp_value":null,"dr_code":801002,"visit_plan_verification_status":1,"visit_plan_verification_by":"10.36","visit_plan_verification_date":"2019-06-13T11:37:46.727","visit_real_verification_status":0,"visit_real_verification_by":null,"visit_real_verification_date":null,"visit_date_plan_saved":"2019-06-12T00:00:00","visit_date_plan_updated":null,"visit_date_realization_saved":null,"visit_coverage_plan":null,"visit_coverage_real":null,"visit_sign_id":null,"visit_sign_image":"","visit_ordinat":null,"visit_product_count":1,"visit_comment":null},{"visit_id":"V19114339","rep_id":"11.03","visit_date_plan":"2019-06-25T00:00:00","visit_plan":1,"visit_code":null,"visit_realization":0,"visit_info":null,"visit_sp":null,"visit_sp_value":null,"dr_code":801011,"visit_plan_verification_status":1,"visit_plan_verification_by":"10.36","visit_plan_verification_date":"2019-06-13T11:37:46.727","visit_real_verification_status":0,"visit_real_verification_by":null,"visit_real_verification_date":null,"visit_date_plan_saved":"2019-06-12T00:00:00","visit_date_plan_updated":null,"visit_date_realization_saved":null,"visit_coverage_plan":null,"visit_coverage_real":null,"visit_sign_id":null,"visit_sign_image":"","visit_ordinat":null,"visit_product_count":1,"visit_comment":null},{"visit_id":"V19114340","rep_id":"11.03","visit_date_plan":"2019-06-25T00:00:00","visit_plan":1,"visit_code":null,"visit_realization":0,"visit_info":null,"visit_sp":null,"visit_sp_value":null,"dr_code":801013,"visit_plan_verification_status":1,"visit_plan_verification_by":"10.36","visit_plan_verification_date":"2019-06-13T11:37:46.727","visit_real_verification_status":0,"visit_real_verification_by":null,"visit_real_verification_date":null,"visit_date_plan_saved":"2019-06-12T00:00:00","visit_date_plan_updated":null,"visit_date_realization_saved":null,"visit_coverage_plan":null,"visit_coverage_real":null,"visit_sign_id":null,"visit_sign_image":"","visit_ordinat":null,"visit_product_count":2,"visit_comment":null},{"visit_id":"V19114341","rep_id":"11.03","visit_date_plan":"2019-06-25T00:00:00","visit_plan":1,"visit_code":null,"visit_realization":0,"visit_info":null,"visit_sp":null,"visit_sp_value":null,"dr_code":801027,"visit_plan_verification_status":1,"visit_plan_verification_by":"10.36","visit_plan_verification_date":"2019-06-13T11:37:46.727","visit_real_verification_status":0,"visit_real_verification_by":null,"visit_real_verification_date":null,"visit_date_plan_saved":"2019-06-12T00:00:00","visit_date_plan_updated":null,"visit_date_realization_saved":null,"visit_coverage_plan":null,"visit_coverage_real":null,"visit_sign_id":null,"visit_sign_image":"","visit_ordinat":null,"visit_product_count":1,"visit_comment":null},{"visit_id":"V19114342","rep_id":"11.03","visit_date_plan":"2019-06-25T00:00:00","visit_plan":1,"visit_code":null,"visit_realization":0,"visit_info":null,"visit_sp":null,"visit_sp_value":null,"dr_code":821009,"visit_plan_verification_status":1,"visit_plan_verification_by":"10.36","visit_plan_verification_date":"2019-06-13T11:37:46.727","visit_real_verification_status":0,"visit_real_verification_by":null,"visit_real_verification_date":null,"visit_date_plan_saved":"2019-06-12T00:00:00","visit_date_plan_updated":null,"visit_date_realization_saved":null,"visit_coverage_plan":null,"visit_coverage_real":null,"visit_sign_id":null,"visit_sign_image":"","visit_ordinat":null,"visit_product_count":1,"visit_comment":null},{"visit_id":"V19114343","rep_id":"11.03","visit_date_plan":"2019-06-25T00:00:00","visit_plan":1,"visit_code":null,"visit_realization":0,"visit_info":null,"visit_sp":null,"visit_sp_value":null,"dr_code":3142006,"visit_plan_verification_status":1,"visit_plan_verification_by":"10.36","visit_plan_verification_date":"2019-06-13T11:37:46.727","visit_real_verification_status":0,"visit_real_verification_by":null,"visit_real_verification_date":null,"visit_date_plan_saved":"2019-06-12T00:00:00","visit_date_plan_updated":null,"visit_date_realization_saved":null,"visit_coverage_plan":null,"visit_coverage_real":null,"visit_sign_id":null,"visit_sign_image":"","visit_ordinat":null,"visit_product_count":1,"visit_comment":null},{"visit_id":"V19114355","rep_id":"11.03","visit_date_plan":"2019-06-25T00:00:00","visit_plan":1,"visit_code":null,"visit_realization":0,"visit_info":null,"visit_sp":null,"visit_sp_value":null,"dr_code":821005,"visit_plan_verification_status":1,"visit_plan_verification_by":"10.36","visit_plan_verification_date":"2019-06-13T11:37:46.727","visit_real_verification_status":0,"visit_real_verification_by":null,"visit_real_verification_date":null,"visit_date_plan_saved":"2019-06-12T00:00:00","visit_date_plan_updated":null,"visit_date_realization_saved":null,"visit_coverage_plan":null,"visit_coverage_real":null,"visit_sign_id":null,"visit_sign_image":"","visit_ordinat":null,"visit_product_count":1,"visit_comment":null},{"visit_id":"V19114356","rep_id":"11.03","visit_date_plan":"2019-06-26T00:00:00","visit_plan":1,"visit_code":null,"visit_realization":0,"visit_info":null,"visit_sp":null,"visit_sp_value":null,"dr_code":821021,"visit_plan_verification_status":1,"visit_plan_verification_by":"10.36","visit_plan_verification_date":"2019-06-13T11:37:46.727","visit_real_verification_status":0,"visit_real_verification_by":null,"visit_real_verification_date":null,"visit_date_plan_saved":"2019-06-12T00:00:00","visit_date_plan_updated":null,"visit_date_realization_saved":null,"visit_coverage_plan":null,"visit_coverage_real":null,"visit_sign_id":null,"visit_sign_image":"","visit_ordinat":null,"visit_product_count":null,"visit_comment":null},{"visit_id":"V19114357","rep_id":"11.03","visit_date_plan":"2019-06-26T00:00:00","visit_plan":1,"visit_code":null,"visit_realization":0,"visit_info":null,"visit_sp":null,"visit_sp_value":null,"dr_code":3142007,"visit_plan_verification_status":1,"visit_plan_verification_by":"10.36","visit_plan_verification_date":"2019-06-13T11:37:46.727","visit_real_verification_status":0,"visit_real_verification_by":null,"visit_real_verification_date":null,"visit_date_plan_saved":"2019-06-12T00:00:00","visit_date_plan_updated":null,"visit_date_realization_saved":null,"visit_coverage_plan":null,"visit_coverage_real":null,"visit_sign_id":null,"visit_sign_image":"","visit_ordinat":null,"visit_product_count":null,"visit_comment":null},{"visit_id":"V19114358","rep_id":"11.03","visit_date_plan":"2019-06-26T00:00:00","visit_plan":1,"visit_code":null,"visit_realization":0,"visit_info":null,"visit_sp":null,"visit_sp_value":null,"dr_code":801030,"visit_plan_verification_status":1,"visit_plan_verification_by":"10.36","visit_plan_verification_date":"2019-06-13T11:37:46.727","visit_real_verification_status":0,"visit_real_verification_by":null,"visit_real_verification_date":null,"visit_date_plan_saved":"2019-06-12T00:00:00","visit_date_plan_updated":null,"visit_date_realization_saved":null,"visit_coverage_plan":null,"visit_coverage_real":null,"visit_sign_id":null,"visit_sign_image":"","visit_ordinat":null,"visit_product_count":null,"visit_comment":null},{"visit_id":"V19114359","rep_id":"11.03","visit_date_plan":"2019-06-26T00:00:00","visit_plan":1,"visit_code":null,"visit_realization":0,"visit_info":null,"visit_sp":null,"visit_sp_value":null,"dr_code":801005,"visit_plan_verification_status":1,"visit_plan_verification_by":"10.36","visit_plan_verification_date":"2019-06-13T11:37:46.727","visit_real_verification_status":0,"visit_real_verification_by":null,"visit_real_verification_date":null,"visit_date_plan_saved":"2019-06-12T00:00:00","visit_date_plan_updated":null,"visit_date_realization_saved":null,"visit_coverage_plan":null,"visit_coverage_real":null,"visit_sign_id":null,"visit_sign_image":"","visit_ordinat":null,"visit_product_count":1,"visit_comment":null},{"visit_id":"V19114360","rep_id":"11.03","visit_date_plan":"2019-06-27T00:00:00","visit_plan":1,"visit_code":null,"visit_realization":0,"visit_info":null,"visit_sp":null,"visit_sp_value":null,"dr_code":801024,"visit_plan_verification_status":1,"visit_plan_verification_by":"10.36","visit_plan_verification_date":"2019-06-13T11:37:46.727","visit_real_verification_status":0,"visit_real_verification_by":null,"visit_real_verification_date":null,"visit_date_plan_saved":"2019-06-12T00:00:00","visit_date_plan_updated":null,"visit_date_realization_saved":null,"visit_coverage_plan":null,"visit_coverage_real":null,"visit_sign_id":null,"visit_sign_image":"","visit_ordinat":null,"visit_product_count":1,"visit_comment":null},{"visit_id":"V19114361","rep_id":"11.03","visit_date_plan":"2019-06-27T00:00:00","visit_plan":1,"visit_code":null,"visit_realization":0,"visit_info":null,"visit_sp":null,"visit_sp_value":null,"dr_code":821004,"visit_plan_verification_status":1,"visit_plan_verification_by":"10.36","visit_plan_verification_date":"2019-06-13T11:37:46.727","visit_real_verification_status":0,"visit_real_verification_by":null,"visit_real_verification_date":null,"visit_date_plan_saved":"2019-06-12T00:00:00","visit_date_plan_updated":null,"visit_date_realization_saved":null,"visit_coverage_plan":null,"visit_coverage_real":null,"visit_sign_id":null,"visit_sign_image":"","visit_ordinat":null,"visit_product_count":1,"visit_comment":null},{"visit_id":"V19114362","rep_id":"11.03","visit_date_plan":"2019-06-27T00:00:00","visit_plan":1,"visit_code":null,"visit_realization":0,"visit_info":null,"visit_sp":null,"visit_sp_value":null,"dr_code":821018,"visit_plan_verification_status":1,"visit_plan_verification_by":"10.36","visit_plan_verification_date":"2019-06-13T11:37:46.727","visit_real_verification_status":0,"visit_real_verification_by":null,"visit_real_verification_date":null,"visit_date_plan_saved":"2019-06-12T00:00:00","visit_date_plan_updated":null,"visit_date_realization_saved":null,"visit_coverage_plan":null,"visit_coverage_real":null,"visit_sign_id":null,"visit_sign_image":"","visit_ordinat":null,"visit_product_count":2,"visit_comment":null},{"visit_id":"V19114363","rep_id":"11.03","visit_date_plan":"2019-06-27T00:00:00","visit_plan":1,"visit_code":null,"visit_realization":0,"visit_info":null,"visit_sp":null,"visit_sp_value":null,"dr_code":2141006,"visit_plan_verification_status":1,"visit_plan_verification_by":"10.36","visit_plan_verification_date":"2019-06-13T11:37:46.727","visit_real_verification_status":0,"visit_real_verification_by":null,"visit_real_verification_date":null,"visit_date_plan_saved":"2019-06-12T00:00:00","visit_date_plan_updated":null,"visit_date_realization_saved":null,"visit_coverage_plan":null,"visit_coverage_real":null,"visit_sign_id":null,"visit_sign_image":"","visit_ordinat":null,"visit_product_count":1,"visit_comment":null},{"visit_id":"V19114364","rep_id":"11.03","visit_date_plan":"2019-06-27T00:00:00","visit_plan":1,"visit_code":null,"visit_realization":0,"visit_info":null,"visit_sp":null,"visit_sp_value":null,"dr_code":3142010,"visit_plan_verification_status":1,"visit_plan_verification_by":"10.36","visit_plan_verification_date":"2019-06-13T11:37:46.727","visit_real_verification_status":0,"visit_real_verification_by":null,"visit_real_verification_date":null,"visit_date_plan_saved":"2019-06-12T00:00:00","visit_date_plan_updated":null,"visit_date_realization_saved":null,"visit_coverage_plan":null,"visit_coverage_real":null,"visit_sign_id":null,"visit_sign_image":"","visit_ordinat":null,"visit_product_count":1,"visit_comment":null},{"visit_id":"V19114365","rep_id":"11.03","visit_date_plan":"2019-06-27T00:00:00","visit_plan":1,"visit_code":null,"visit_realization":0,"visit_info":null,"visit_sp":null,"visit_sp_value":null,"dr_code":353143,"visit_plan_verification_status":1,"visit_plan_verification_by":"10.36","visit_plan_verification_date":"2019-06-13T11:37:46.727","visit_real_verification_status":0,"visit_real_verification_by":null,"visit_real_verification_date":null,"visit_date_plan_saved":"2019-06-12T00:00:00","visit_date_plan_updated":null,"visit_date_realization_saved":null,"visit_coverage_plan":null,"visit_coverage_real":null,"visit_sign_id":null,"visit_sign_image":"","visit_ordinat":null,"visit_product_count":1,"visit_comment":null},{"visit_id":"V19114377","rep_id":"11.03","visit_date_plan":"2019-06-28T00:00:00","visit_plan":1,"visit_code":null,"visit_realization":0,"visit_info":null,"visit_sp":null,"visit_sp_value":null,"dr_code":455018,"visit_plan_verification_status":1,"visit_plan_verification_by":"10.36","visit_plan_verification_date":"2019-06-13T11:37:46.727","visit_real_verification_status":0,"visit_real_verification_by":null,"visit_real_verification_date":null,"visit_date_plan_saved":"2019-06-12T00:00:00","visit_date_plan_updated":null,"visit_date_realization_saved":null,"visit_coverage_plan":null,"visit_coverage_real":null,"visit_sign_id":null,"visit_sign_image":"","visit_ordinat":null,"visit_product_count":1,"visit_comment":null},{"visit_id":"V19114378","rep_id":"11.03","visit_date_plan":"2019-06-28T00:00:00","visit_plan":1,"visit_code":null,"visit_realization":0,"visit_info":null,"visit_sp":null,"visit_sp_value":null,"dr_code":801025,"visit_plan_verification_status":1,"visit_plan_verification_by":"10.36","visit_plan_verification_date":"2019-06-13T11:37:46.727","visit_real_verification_status":0,"visit_real_verification_by":null,"visit_real_verification_date":null,"visit_date_plan_saved":"2019-06-12T00:00:00","visit_date_plan_updated":null,"visit_date_realization_saved":null,"visit_coverage_plan":null,"visit_coverage_real":null,"visit_sign_id":null,"visit_sign_image":"","visit_ordinat":null,"visit_product_count":1,"visit_comment":null},{"visit_id":"V19114379","rep_id":"11.03","visit_date_plan":"2019-06-28T00:00:00","visit_plan":1,"visit_code":null,"visit_realization":0,"visit_info":null,"visit_sp":null,"visit_sp_value":null,"dr_code":821002,"visit_plan_verification_status":1,"visit_plan_verification_by":"10.36","visit_plan_verification_date":"2019-06-13T11:37:46.727","visit_real_verification_status":0,"visit_real_verification_by":null,"visit_real_verification_date":null,"visit_date_plan_saved":"2019-06-12T00:00:00","visit_date_plan_updated":null,"visit_date_realization_saved":null,"visit_coverage_plan":null,"visit_coverage_real":null,"visit_sign_id":null,"visit_sign_image":"","visit_ordinat":null,"visit_product_count":1,"visit_comment":null},{"visit_id":"V19114380","rep_id":"11.03","visit_date_plan":"2019-06-28T00:00:00","visit_plan":1,"visit_code":null,"visit_realization":0,"visit_info":null,"visit_sp":null,"visit_sp_value":null,"dr_code":2141005,"visit_plan_verification_status":1,"visit_plan_verification_by":"10.36","visit_plan_verification_date":"2019-06-13T11:37:46.727","visit_real_verification_status":0,"visit_real_verification_by":null,"visit_real_verification_date":null,"visit_date_plan_saved":"2019-06-12T00:00:00","visit_date_plan_updated":null,"visit_date_realization_saved":null,"visit_coverage_plan":null,"visit_coverage_real":null,"visit_sign_id":null,"visit_sign_image":"","visit_ordinat":null,"visit_product_count":1,"visit_comment":null},{"visit_id":"V19114381","rep_id":"11.03","visit_date_plan":"2019-06-28T00:00:00","visit_plan":1,"visit_code":null,"visit_realization":0,"visit_info":null,"visit_sp":null,"visit_sp_value":null,"dr_code":2141008,"visit_plan_verification_status":1,"visit_plan_verification_by":"10.36","visit_plan_verification_date":"2019-06-13T11:37:46.727","visit_real_verification_status":0,"visit_real_verification_by":null,"visit_real_verification_date":null,"visit_date_plan_saved":"2019-06-12T00:00:00","visit_date_plan_updated":null,"visit_date_realization_saved":null,"visit_coverage_plan":null,"visit_coverage_real":null,"visit_sign_id":null,"visit_sign_image":"","visit_ordinat":null,"visit_product_count":1,"visit_comment":null},{"visit_id":"V19114382","rep_id":"11.03","visit_date_plan":"2019-06-28T00:00:00","visit_plan":1,"visit_code":null,"visit_realization":0,"visit_info":null,"visit_sp":null,"visit_sp_value":null,"dr_code":353110,"visit_plan_verification_status":1,"visit_plan_verification_by":"10.36","visit_plan_verification_date":"2019-06-13T11:37:46.727","visit_real_verification_status":0,"visit_real_verification_by":null,"visit_real_verification_date":null,"visit_date_plan_saved":"2019-06-12T00:00:00","visit_date_plan_updated":null,"visit_date_realization_saved":null,"visit_coverage_plan":null,"visit_coverage_real":null,"visit_sign_id":null,"visit_sign_image":"","visit_ordinat":null,"visit_product_count":1,"visit_comment":null},{"visit_id":"V19114383","rep_id":"11.03","visit_date_plan":"2019-06-26T00:00:00","visit_plan":1,"visit_code":null,"visit_realization":0,"visit_info":null,"visit_sp":null,"visit_sp_value":null,"dr_code":3142009,"visit_plan_verification_status":1,"visit_plan_verification_by":"10.36","visit_plan_verification_date":"2019-06-13T11:37:46.727","visit_real_verification_status":0,"visit_real_verification_by":null,"visit_real_verification_date":null,"visit_date_plan_saved":"2019-06-12T00:00:00","visit_date_plan_updated":null,"visit_date_realization_saved":null,"visit_coverage_plan":null,"visit_coverage_real":null,"visit_sign_id":null,"visit_sign_image":"","visit_ordinat":null,"visit_product_count":1,"visit_comment":null}]
